python_kdeploy/__init__.py
python_kdeploy/entry.py
python_kdeploy/invoke_generator/__init__.py
python_kdeploy/invoke_generator/datatypes.py
python_kdeploy/invoke_generator/helpers.py
python_kdeploy/invoke_generator/service.temp
python_kdeploy/invoke_generator/settings.py
python_kdeploy-0.1.2.dist-info/entry_points.txt
python_kdeploy-0.1.2.dist-info/LICENSE
python_kdeploy-0.1.2.dist-info/WHEEL
python_kdeploy-0.1.2.dist-info/METADATA
python_kdeploy-0.1.2.dist-info/RECORD
